nameko_slack/__init__.py
nameko_slack/constants.py
nameko_slack/rtm.py
nameko_slack/web.py
nameko_slack-0.0.6.dist-info/LICENSE
nameko_slack-0.0.6.dist-info/METADATA
nameko_slack-0.0.6.dist-info/WHEEL
nameko_slack-0.0.6.dist-info/top_level.txt
nameko_slack-0.0.6.dist-info/zip-safe
nameko_slack-0.0.6.dist-info/RECORD
